README.md
setup.py
distributions/Binomialdistribution.py
distributions/Gaussiandistribution.py
distributions/Generaldistribution.py
distributions/__init__.py
h1distributions.egg-info/PKG-INFO
h1distributions.egg-info/SOURCES.txt
h1distributions.egg-info/dependency_links.txt
h1distributions.egg-info/not-zip-safe
h1distributions.egg-info/top_level.txt